bluesky/resources/graphics/__init__.py
bluesky/resources/graphics/airport.gif
bluesky/resources/graphics/bluesky.icns
bluesky/resources/graphics/bluesky_icon_256x256.png
bluesky/resources/graphics/icon.gif
bluesky/resources/graphics/mainwindow.ui
bluesky/resources/graphics/menu.dat
bluesky/resources/graphics/scr_cfg.dat
bluesky/resources/graphics/splash.gif
bluesky/resources/graphics/waypoint.gif
bluesky/resources/graphics/world.16384x8192.dds
bluesky/resources/graphics/world.4096x2048.dds
bluesky/resources/graphics/world.8192x4096.dds
bluesky/resources/graphics/world.jpg
bluesky/resources/graphics/acsymbol/acsymbol0.png
bluesky/resources/graphics/acsymbol/acsymbol1.png
bluesky/resources/graphics/acsymbol/acsymbol10.png
bluesky/resources/graphics/acsymbol/acsymbol11.png
bluesky/resources/graphics/acsymbol/acsymbol12.png
bluesky/resources/graphics/acsymbol/acsymbol13.png
bluesky/resources/graphics/acsymbol/acsymbol14.png
bluesky/resources/graphics/acsymbol/acsymbol15.png
bluesky/resources/graphics/acsymbol/acsymbol16.png
bluesky/resources/graphics/acsymbol/acsymbol17.png
bluesky/resources/graphics/acsymbol/acsymbol18.png
bluesky/resources/graphics/acsymbol/acsymbol19.png
bluesky/resources/graphics/acsymbol/acsymbol2.png
bluesky/resources/graphics/acsymbol/acsymbol20.png
bluesky/resources/graphics/acsymbol/acsymbol21.png
bluesky/resources/graphics/acsymbol/acsymbol22.png
bluesky/resources/graphics/acsymbol/acsymbol23.png
bluesky/resources/graphics/acsymbol/acsymbol24.png
bluesky/resources/graphics/acsymbol/acsymbol25.png
bluesky/resources/graphics/acsymbol/acsymbol26.png
bluesky/resources/graphics/acsymbol/acsymbol27.png
bluesky/resources/graphics/acsymbol/acsymbol28.png
bluesky/resources/graphics/acsymbol/acsymbol29.png
bluesky/resources/graphics/acsymbol/acsymbol3.png
bluesky/resources/graphics/acsymbol/acsymbol30.png
bluesky/resources/graphics/acsymbol/acsymbol31.png
bluesky/resources/graphics/acsymbol/acsymbol32.png
bluesky_guidata-2024.12.18.dist-info/METADATA
bluesky_guidata-2024.12.18.dist-info/WHEEL
bluesky_guidata-2024.12.18.dist-info/RECORD
